Workbook

Sheet ①旧格式-输入
A1: 利润表（旧格式 / 现行列报）—— 数据输入区
A2: 行项目 | B2: 符号 | C2: 本期金额 | D2: 上期金额
A3: 营业收入 | B3: 1
A4: 减：营业成本 | B4: -1
A5: 税金及附加 | B5: -1
A6: 销售费用 | B6: -1
A7: 管理费用 | B7: -1
A8: 研发费用 | B8: -1
A9: 财务费用——经营部分（手续费/银行费等） | B9: -1
A10: 其中：利息费用（→筹资类） | B10: -1
A11: 其中：利息收入（→投资类） | B11: 1
A12: 其他收益 | B12: 1
A13: 投资收益 | B13: 1
A14: 公允价值变动收益（按类别归集，默认投资） | B14: 1
... A24: 终止经营损益（税后净额，填正负） | B24: 0
A25: 黄底单元格为手工录入（或接 TB/试算平衡表取数）；符号列驱动输出区正负。留空按 0 处理。

Sheet ②新五分类-输出
A1: 利润表（新列报准则·五分类重排）—— 公式输出区
A2: 类别 | B2: 行项目 | C2: 本期金额 | D2: 上期金额
A3: 【经营类】 | B3: 营业收入 | C3: ='①旧格式-输入'!C3 | D3: ='①旧格式-输入'!D3
B4: 减：营业成本 | C4: ='①旧格式-输入'!C4*-1 | D4: ='①旧格式-输入'!D4*-1
B5: 税金及附加 | C5: ='①旧格式-输入'!C5*-1 | D5: ='①旧格式-输入'!D5*-1
B6: 销售费用 | C6: ='①旧格式-输入'!C6*-1 | D6: ='①旧格式-输入'!D6*-1
B7: 管理费用 | C7: ='①旧格式-输入'!C7*-1 | D7: ='①旧格式-输入'!D7*-1
B8: 研发费用 | C8: ='①旧格式-输入'!C8*-1 | D8: ='①旧格式-输入'!D8*-1
B9: 财务费用——经营部分 | C9: ='①旧格式-输入'!C9*-1 | D9: ='①旧格式-输入'!D9*-1
B10: 信用减值损失 | C10: ='①旧格式-输入'!C15*-1 | D10: ='①旧格式-输入'!D15*-1
B11: 资产减值损失 | C11: ='①旧格式-输入'!C16*-1 | D11: ='①旧格式-输入'!D16*-1
B12: 资产处置收益 | C12: ='①旧格式-输入'!C17*1 | D12: ='①旧格式-输入'!D17*1
B13: 其他收益 | C13: ='①旧格式-输入'!C12*1 | D13: ='①旧格式-输入'!D12*1
B14: 营业外收入（兜底） | C14: ='①旧格式-输入'!C18*1 | D14: ='①旧格式-输入'!D18*1
B15: 减：营业外支出（兜底） | C15: ='①旧格式-输入'!C19*-1 | D15: ='①旧格式-输入'!D19*-1
B16: 汇兑损益——经营 | C16: ='①旧格式-输入'!C20 | D16: ='①旧格式-输入'!D20
A17: 【经营类】 | B17: 经营利润（小计） | C17: =SUM(C3:C16) | D17: =SUM(D3:D16)
A18: 【投资类】 | B18: 投资收益 | C18: ='①旧格式-输入'!C13*1 | D18: ='①旧格式-输入'!D13*1
B19: 利息收入 | C19: ='①旧格式-输入'!C11*1 | D19: ='①旧格式-输入'!D11*1
B20: 公允价值变动收益（归投资） | C20: ='①旧格式-输入'!C14*1 | D20: ='①旧格式-输入'!D14*1
B21: 汇兑损益——投资 | C21: ='①旧格式-输入'!C21 | D21: ='①旧格式-输入'!D21
A22: 【投资类】 | B22: 投资类小计 | C22: =SUM(C18:C21) | D22: =SUM(D18:D21)
A23: 【经营+投资】 | B23: 经营及投资利润 | C23: =C17+C22 | D23: =D17+D22
A24: 【筹资类】 | B24: 利息费用 | C24: ='①旧格式-输入'!C10*-1 | D24: ='①旧格式-输入'!D10*-1
B25: 汇兑损益——筹资 | C25: ='①旧格式-输入'!C22 | D25: ='①旧格式-输入'!D22
A26: 【筹资类】 | B26: 筹资类小计 | C26: =SUM(C24:C25) | D26: =SUM(D24:D25)
A27: 【持续经营·税前】 | B27: 持续经营利润（税前） | C27: =C23-C26 | D27: =D23-D26
A28: 【所得税费用类】 | B28: 所得税费用 | C28: ='①旧格式-输入'!C23*-1 | D28: ='①旧格式-输入'!D23*-1
A29: 【持续经营·税后】 | B29: 持续经营净利润 | C29: =C27-C28 | D29: =D27-D28
A30: 【终止经营类】 | B30: 终止经营损益（税后） | C30: ='①旧格式-输入'!C24 | D30: ='①旧格式-输入'!D24
A31: 【净利润】 | B31: 净利润 | C31: =C29+C30 | D31: =D29+D30
A33: 校验 | B33: 旧表净利润（按旧格式重算） | C33: ='①旧格式-输入'!C3+-'①旧格式-输入'!C4+-'①旧格式-输入'!C5+-'①旧格式-输入'!C6+-'①旧格式-输入'!C7+-'①旧格式-输入'!C8+-'①旧格式-输入'!C9+-'①旧格式-输入'!C10+'①旧格式-输入'!C11+'①旧格式-输入'!C12+'①旧格式-输入'!C13+'①旧格式-输入'!C14+-'①旧格式-输入'!C15+-'①旧格式-输入'!C16+'①旧格式-输入'!C17+'①旧格式-输入'!C18+-'①旧格式-输入'!C19+'①旧格式-输入'!C20+'①旧格式-输入'!C21+'①旧格式-输入'!C22+-'①旧格式-输入'!C23+'①旧格式-输入'!C24
B34: 新表净利润（输出区） | C34: =C31
B35: 差异（应为 0） | C35: =C34-C33 | D35: 若≠0，检查分类或符号录入
A37: 本表全部为公式，引用「①旧格式-输入」。改输入→本表自动重排。小计级联：经营利润→经营及投资利润→持续经营利润(税前)→持续经营净利润→净利润。

Sheet ③映射对照
A1: 旧格式行项目 → 五分类 映射对照（准则依据）
A2: 旧格式行项目 | B2: 五分类归属 | C2: 准则依据 / 备注
A3: 营业收入 | B3: 经营类 | C3: 第三十二条：经营类为剩余兜底类别
A4: 减：营业成本 | B4: 经营类 | C4: 主业成本
A5: 税金及附加 | B5: 经营类 | C5: 经营相关税费
A6: 销售费用 | B6: 经营类 | C6: 经营类
A7: 管理费用 | B7: 经营类 | C7: 经营类
A8: 研发费用 | B8: 经营类 | C8: 经营类
A9: 财务费用——经营部分 | B9: 经营类 | C9: 手续费等，非利息收支
A10: 其中：利息费用 | B10: 筹资类 | C10: 第三十四条：利息费用归入筹资类别
A11: 其中：利息收入 | B11: 投资类 | C11: 第三十四条：利息收入归入投资类别（特定资产回报）
A12: 其他收益 | B12: 经营类 | C12: 经营相关政府补助等
A13: 投资收益 | B13: 投资类 | C13: 对联营合营、债权投资等回报
... A24: 终止经营损益 | B24: 终止经营类 | C24: 独立隔离列示，不混入持续经营

Sheet ④2027切换清单
A1: 新列报准则（财会〔2026〕11号）2027 切换 Checklist
A2: A+H / 境外上市：2027-01-01 起执行且需追溯重述对比期（2025、2026）。纯境内上市 2029；非上市 2030。允许提前。
A3: 序号 | B3: 切换事项 | C3: 是否完成 | D3: 责任人 | E3: 备注
A4: 1 | B4: 梳理会计科目体系，确保科目设置与新利润表五分类衔接 | C4: ☐
A5: 2 | B5: 识别「特定主要业务活动」主体（银行/地产/融资租赁等），其投资/筹资损益归入经营类 | C5: ☐ | E5: ★关键点
A6: 3 | B6: 拆分财务费用为：利息收入(投资)/利息费用(筹资)/其他(经营) | C6: ☐
A7: 4 | B7: 汇兑损益按来源拆分至 经营/投资/筹资（跟项目走，勿一把抓进财务费用） | C7: ☐ | E7: ★审计必查
A8: 5 | B8: 公允价值变动损益取消单独项目，按所属类别归集 | C8: ☐
A9: 6 | B9: 终止经营损益独立隔离列示，不混入持续经营 | C9: ☐
A10: 7 | B10: 追溯重述对比期间（2025、2026）财务数据至新五分类格式 | C10: ☐ | E10: ★2027强制
A11: 8 | B11: 识别并披露管理层业绩指标(MPM)，附注说明内涵与计算方式（第六十六条） | C11: ☐ | E11: ★突破点
A12: 9 | B12: 评估信息系统 / 报表模块改造，支持五分类取数与小计级联 | C12: ☐
A13: 10 | B13: 关键判断（特定主要业务活动、MPM界定）形成书面记录备查 | C13: ☐
A14: 11 | B14: 财政部应用指南 / 会计科目修订出台后，复核并调整分类口径 | C14: ☐
